elt_tools_aio/__init__.py
elt_tools_aio/client.py
elt_tools_aio/engines.py
elt_tools_aio/settings_example.py
elt_tools_aio/tests/__init__.py
elt_tools_aio/tests/test_client.py
elt_tools_aio-0.1.0.dist-info/entry_points.txt
elt_tools_aio-0.1.0.dist-info/WHEEL
elt_tools_aio-0.1.0.dist-info/METADATA
elt_tools_aio-0.1.0.dist-info/RECORD
