Metadata-Version: 2.1
Name: elt-tools-aio
Version: 0.1.0
Summary: Tools for monitoring and troubleshooting ELT arrangements.
Home-page: https://github.com/dewaldabrie/elt_tools_aio/
License: MIT
Keywords: BigQuery,SQL,SQLAlchemy,ETL,AsyncIO,Google Cloud
Author: Dewald Abrie
Author-email: dewaldabrie@gmail.com
Maintainer: Dewald Abrie
Maintainer-email: dewaldabrie@gmail.com
Requires-Python: >=3.7,<4.0
Classifier: License :: OSI Approved :: MIT License
Classifier: Programming Language :: Python :: 3
Classifier: Programming Language :: Python :: 3.7
Classifier: Programming Language :: Python :: 3.8
Requires-Dist: PyMySQL
Requires-Dist: psycopg2
Requires-Dist: pybigquery
Requires-Dist: sqlalchemy-aio
Requires-Dist: sqlalchemy-redshift
Project-URL: Documentation, https://github.com/dewaldabrie/elt_tools_aio/
Project-URL: Repository, https://github.com/dewaldabrie/elt_tools_aio/
Project-URL: issues, https://github.com/dewaldabrie/elt_tools_aio/issues
